handsoff/__init__.py
handsoff/__main__.py
handsoff/settings.json
handsoff/modules/Commands_generate.py
handsoff/modules/__init__.py
handsoff/modules/cli.py
handsoff/modules/side_effects.py
handsoff-1.2.0.dist-info/licenses/LICENSE
handsoff-1.2.0.dist-info/METADATA
handsoff-1.2.0.dist-info/WHEEL
handsoff-1.2.0.dist-info/entry_points.txt
handsoff-1.2.0.dist-info/top_level.txt
handsoff-1.2.0.dist-info/RECORD
