Metadata-Version: 2.4
Name: handsoff
Version: 1.2.0
Summary: Auto file tranfer with scp command.
Author-email: MovingJu <movingju06@gmail.com>
Classifier: Programming Language :: Python :: 3
Requires-Python: >=3.11.13
License-File: LICENSE
Requires-Dist: dotenv>=0.9.9
Dynamic: license-file
